evalne/__init__.py
evalne/__main__.py
evalne/evaluation/__init__.py
evalne/evaluation/edge_embeddings.py
evalne/evaluation/evaluator.py
evalne/evaluation/pipeline.py
evalne/evaluation/score.py
evalne/evaluation/split.py
evalne/methods/__init__.py
evalne/methods/katz.py
evalne/methods/similarity.py
evalne/tests/__init__.py
evalne/tests/test_baselines.py
evalne/tests/test_edgeembeds.py
evalne/tests/test_nr_sampling.py
evalne/tests/test_preprocess.py
evalne/tests/test_spantree.py
evalne/tests/test_visualize.py
evalne/utils/__init__.py
evalne/utils/preprocess.py
evalne/utils/split_train_test.py
evalne/utils/util.py
evalne/utils/viz_utils.py
evalne-0.4.0.dist-info/LICENSE
evalne-0.4.0.dist-info/METADATA
evalne-0.4.0.dist-info/WHEEL
evalne-0.4.0.dist-info/top_level.txt
evalne-0.4.0.dist-info/RECORD
