Metadata-Version: 2.1
Name: evalne
Version: 0.4.0
Summary: Open Source Network Embedding Evaluation toolkit
Home-page: https://github.com/Dru-Mara/EvalNE
Author: Alexandru Mara
Author-email: alexandru.mara@ugent.be
License: MIT License
Keywords: evaluation embedding link-prediction sign-prediction node-classification network-reconstruction networks graphs visualization
Classifier: Intended Audience :: Science/Research
Classifier: Intended Audience :: Developers
Classifier: Topic :: Scientific/Engineering :: Information Analysis
Classifier: Topic :: Software Development
Classifier: Programming Language :: Python :: 3
Classifier: License :: OSI Approved :: MIT License
Classifier: Natural Language :: English
Classifier: Operating System :: OS Independent
Requires-Python: >3.7
License-File: LICENSE
Requires-Dist: numpy
Requires-Dist: scikit-learn
Requires-Dist: networkx
Requires-Dist: scipy
Requires-Dist: matplotlib
Requires-Dist: pandas
Requires-Dist: pyparsing
Requires-Dist: tqdm
Requires-Dist: kiwisolver
Requires-Dist: joblib
